README.md
setup.py
occv/__init__.py
occv/hough_detect_line.py
occv/img_brightness.py
occv/img_fisheye_mask.py
occv/img_match_graph.py
occv/img_statistic.py
occv/img_to_bin.py
occv/imtools.py
occv/pil_demo.py
occv/pylab_demo.py
occv.egg-info/PKG-INFO
occv.egg-info/SOURCES.txt
occv.egg-info/dependency_links.txt
occv.egg-info/entry_points.txt
occv.egg-info/requires.txt
occv.egg-info/top_level.txt
occv/fft/__init__.py
occv/fft/fft_denoise_image.py
occv/fft/fft_fde.py
occv/fft/fft_ocv_01.py
occv/fft/fft_ocv_02.py
occv/fft/fft_ocv_hpf.py