Metadata-Version: 2.1
Name: occv
Version: 1.0.0
Summary: Open Chenguang Computer Vision library
Home-page: https://cv.cgabc.xyz
Author: Gavin Gao
Author-email: cggos@outlook.com
License: UNKNOWN
Platform: any
Requires-Python: >3.6
